SimpleWin32/__init__.py
SimpleWin32/simplewin32.py
SimpleWin32-0.1.5.dist-info/LICENSE.txt
SimpleWin32-0.1.5.dist-info/METADATA
SimpleWin32-0.1.5.dist-info/WHEEL
SimpleWin32-0.1.5.dist-info/top_level.txt
SimpleWin32-0.1.5.dist-info/RECORD
