Metadata-Version: 2.1
Name: SimpleWin32
Version: 0.1.5
Summary: 项目介绍
Home-page: 
Author: 测码范晔
Author-email: 1538379200@qq.com
License: UNKNOWN
Platform: UNKNOWN
Classifier: Programming Language :: Python :: 3
Classifier: License :: OSI Approved :: MIT License
Classifier: Operating System :: OS Independent
License-File: LICENSE.txt
Requires-Dist: pywin32
